{
	"materials": [
		{
			"name": "steel",
			"properties": { "E": 2e11, "G": 7.692308e10, "nu": 0.3, "rho": 7850 }
		}
	],

	"sections": [
		{
			"name": "w150x13",
			"area": 1.63e-3,
			"inertias": { "Ix": 1.39e-8, "Iy": 6.2e-6, "Iz": 8.28e-7 }
		}
	],

	"nodes": [
		{ "name": "N1", "position": [0, 0, 0] },
		{ "name": "N2", "position": [5, 5, 5] },
		{ "name": "N3", "position": [5, 5, 0] }
	],

	"bars": [
		{
			"name": "B1",
			"start_node": "N1",
			"end_node": "N2",
			"section": "w150x13",
			"material": "steel",
			"rotation": 45,
			"releases": []
		},
		{
			"name": "B2",
			"start_node": "N2",
			"end_node": "N3",
			"section": "w150x13",
			"material": "steel",
			"rotation": 0,
			"releases": []
		}
	],

	"supports": [
		{
			"node": "N1",
			"supports": { "Dx": true, "Dy": true, "Dz": true, "Rx": true, "Ry": true, "Rz": true }
		},
		{
			"node": "N3",
			"supports": { "Dx": true, "Dy": true, "Dz": true, "Rx": true, "Ry": true, "Rz": true }
		}
	],

	"loads": [
		{
			"name": "L1",
			"nodes": [
				{
					"name": "F1",
					"node": "N2",
					"loads": { "Fx": 1e3, "Fy": 2e3, "Fz": 3e3, "Mx": 4e3, "My": 5e3, "Mz": 6e3 }
				}
			],
			"bars": {
				"points": {
					"bar": "B1",
					"system": "local",
					"position": 1.5,
					"loads": { "Fx": 0, "Fy": 0, "Fz": 0, "Mx": 0, "My": 0, "Mz": 0 }
				},
				"distributed": {
					"bar": "B2",
					"system": "local",
					"position": [0.5, 3.5],
					"loads": {
						"Fx": [0, 0],
						"Fy": [0, 0],
						"Fz": [0, 0],
						"Mx": [0, 0],
						"My": [0, 0],
						"Mz": [0, 0]
					}
				}
			}
		}
	]
}
